{
   "results" : [
      {
         "address_components" : [
            {
               "long_name" : "60",
               "short_name" : "60",
               "types" : [ "street_number" ]
            },
            {
               "long_name" : "Brookdale Avenue",
               "short_name" : "Brookdale Ave",
               "types" : [ "route" ]
            },
            {
               "long_name" : "Bedford Park",
               "short_name" : "Bedford Park",
               "types" : [ "neighborhood", "political" ]
            },
            {
               "long_name" : "Old Toronto",
               "short_name" : "Old Toronto",
               "types" : [ "sublocality", "political" ]
            },
            {
               "long_name" : "Toronto",
               "short_name" : "Toronto",
               "types" : [ "locality", "political" ]
            },
            {
               "long_name" : "Toronto Division",
               "short_name" : "Toronto Division",
               "types" : [ "administrative_area_level_2", "political" ]
            },
            {
               "long_name" : "Ontario",
               "short_name" : "ON",
               "types" : [ "administrative_area_level_1", "political" ]
            },
            {
               "long_name" : "Canada",
               "short_name" : "CA",
               "types" : [ "country", "political" ]
            },
            {
               "long_name" : "M5M 1P3",
               "short_name" : "M5M 1P3",
               "types" : [ "postal_code" ]
            }
         ],
         "formatted_address" : "60 Brookdale Avenue, Toronto, ON M5M 1P3, Canada",
         "geometry" : {
            "bounds" : {
               "northeast" : {
                  "lat" : 43.7295567,
                  "lng" : -79.40544079999999
               },
               "southwest" : {
                  "lat" : 43.7295439,
                  "lng" : -79.40544600000001
               }
            },
            "location" : {
               "lat" : 43.7295567,
               "lng" : -79.40544600000001
            },
            "location_type" : "RANGE_INTERPOLATED",
            "viewport" : {
               "northeast" : {
                  "lat" : 43.7308992802915,
                  "lng" : -79.4040944197085
               },
               "southwest" : {
                  "lat" : 43.7282013197085,
                  "lng" : -79.40679238029152
               }
            }
         },
         "types" : [ "street_address" ]
      }
   ],
   "status" : "OK"
}
