{
   "results" : [
      {
         "address_components" : [
            {
               "long_name" : "237",
               "short_name" : "237",
               "types" : [ "street_number" ]
            },
            {
               "long_name" : "Bartlett Avenue",
               "short_name" : "Bartlett Ave",
               "types" : [ "route" ]
            },
            {
               "long_name" : "Dovercourt Park",
               "short_name" : "Dovercourt Park",
               "types" : [ "neighborhood", "political" ]
            },
            {
               "long_name" : "Old Toronto",
               "short_name" : "Old Toronto",
               "types" : [ "sublocality", "political" ]
            },
            {
               "long_name" : "Toronto",
               "short_name" : "Toronto",
               "types" : [ "locality", "political" ]
            },
            {
               "long_name" : "Toronto Division",
               "short_name" : "Toronto Division",
               "types" : [ "administrative_area_level_2", "political" ]
            },
            {
               "long_name" : "Ontario",
               "short_name" : "ON",
               "types" : [ "administrative_area_level_1", "political" ]
            },
            {
               "long_name" : "Canada",
               "short_name" : "CA",
               "types" : [ "country", "political" ]
            },
            {
               "long_name" : "M6H 3G3",
               "short_name" : "M6H 3G3",
               "types" : [ "postal_code" ]
            }
         ],
         "formatted_address" : "237 Bartlett Avenue, Toronto, ON M6H 3G3, Canada",
         "geometry" : {
            "location" : {
               "lat" : 43.6670678,
               "lng" : -79.435502
            },
            "location_type" : "ROOFTOP",
            "viewport" : {
               "northeast" : {
                  "lat" : 43.6684167802915,
                  "lng" : -79.43415301970849
               },
               "southwest" : {
                  "lat" : 43.6657188197085,
                  "lng" : -79.4368509802915
               }
            }
         },
         "types" : [ "street_address" ]
      }
   ],
   "status" : "OK"
}
