{
   "results" : [
      {
         "address_components" : [
            {
               "long_name" : "43",
               "short_name" : "43",
               "types" : [ "street_number" ]
            },
            {
               "long_name" : "Branstone Road",
               "short_name" : "Branstone Rd",
               "types" : [ "route" ]
            },
            {
               "long_name" : "Fairbank",
               "short_name" : "Fairbank",
               "types" : [ "neighborhood", "political" ]
            },
            {
               "long_name" : "York",
               "short_name" : "York",
               "types" : [ "sublocality", "political" ]
            },
            {
               "long_name" : "Toronto",
               "short_name" : "Toronto",
               "types" : [ "locality", "political" ]
            },
            {
               "long_name" : "Toronto Division",
               "short_name" : "Toronto Division",
               "types" : [ "administrative_area_level_2", "political" ]
            },
            {
               "long_name" : "Ontario",
               "short_name" : "ON",
               "types" : [ "administrative_area_level_1", "political" ]
            },
            {
               "long_name" : "Canada",
               "short_name" : "CA",
               "types" : [ "country", "political" ]
            },
            {
               "long_name" : "M6E 4E3",
               "short_name" : "M6E 4E3",
               "types" : [ "postal_code" ]
            }
         ],
         "formatted_address" : "43 Branstone Road, York, ON M6E 4E3, Canada",
         "geometry" : {
            "bounds" : {
               "northeast" : {
                  "lat" : 43.692254,
                  "lng" : -79.45366059999999
               },
               "southwest" : {
                  "lat" : 43.6922501,
                  "lng" : -79.4536782
               }
            },
            "location" : {
               "lat" : 43.692254,
               "lng" : -79.45366059999999
            },
            "location_type" : "RANGE_INTERPOLATED",
            "viewport" : {
               "northeast" : {
                  "lat" : 43.6936010302915,
                  "lng" : -79.45232041970849
               },
               "southwest" : {
                  "lat" : 43.6909030697085,
                  "lng" : -79.45501838029149
               }
            }
         },
         "types" : [ "street_address" ]
      }
   ],
   "status" : "OK"
}
