{
   "results" : [
      {
         "address_components" : [
            {
               "long_name" : "112",
               "short_name" : "112",
               "types" : [ "street_number" ]
            },
            {
               "long_name" : "Balmoral Avenue",
               "short_name" : "Balmoral Ave",
               "types" : [ "route" ]
            },
            {
               "long_name" : "Midtown Toronto",
               "short_name" : "Midtown Toronto",
               "types" : [ "neighborhood", "political" ]
            },
            {
               "long_name" : "Old Toronto",
               "short_name" : "Old Toronto",
               "types" : [ "sublocality", "political" ]
            },
            {
               "long_name" : "Toronto",
               "short_name" : "Toronto",
               "types" : [ "locality", "political" ]
            },
            {
               "long_name" : "Toronto Division",
               "short_name" : "Toronto Division",
               "types" : [ "administrative_area_level_2", "political" ]
            },
            {
               "long_name" : "Ontario",
               "short_name" : "ON",
               "types" : [ "administrative_area_level_1", "political" ]
            },
            {
               "long_name" : "Canada",
               "short_name" : "CA",
               "types" : [ "country", "political" ]
            },
            {
               "long_name" : "M4V 1J5",
               "short_name" : "M4V 1J5",
               "types" : [ "postal_code" ]
            }
         ],
         "formatted_address" : "112 Balmoral Avenue, Toronto, ON M4V 1J5, Canada",
         "geometry" : {
            "location" : {
               "lat" : 43.6849975,
               "lng" : -79.3981502
            },
            "location_type" : "ROOFTOP",
            "viewport" : {
               "northeast" : {
                  "lat" : 43.6863464802915,
                  "lng" : -79.39680121970851
               },
               "southwest" : {
                  "lat" : 43.68364851970851,
                  "lng" : -79.39949918029151
               }
            }
         },
         "types" : [ "street_address" ]
      }
   ],
   "status" : "OK"
}
