{
   "results" : [
      {
         "address_components" : [
            {
               "long_name" : "14",
               "short_name" : "14",
               "types" : [ "street_number" ]
            },
            {
               "long_name" : "Binswood Avenue",
               "short_name" : "Binswood Ave",
               "types" : [ "route" ]
            },
            {
               "long_name" : "Woodbine Heights",
               "short_name" : "Woodbine Heights",
               "types" : [ "neighborhood", "political" ]
            },
            {
               "long_name" : "East York",
               "short_name" : "East York",
               "types" : [ "sublocality", "political" ]
            },
            {
               "long_name" : "Toronto",
               "short_name" : "Toronto",
               "types" : [ "locality", "political" ]
            },
            {
               "long_name" : "Toronto Division",
               "short_name" : "Toronto Division",
               "types" : [ "administrative_area_level_2", "political" ]
            },
            {
               "long_name" : "Ontario",
               "short_name" : "ON",
               "types" : [ "administrative_area_level_1", "political" ]
            },
            {
               "long_name" : "Canada",
               "short_name" : "CA",
               "types" : [ "country", "political" ]
            },
            {
               "long_name" : "M4C 3N3",
               "short_name" : "M4C 3N3",
               "types" : [ "postal_code" ]
            }
         ],
         "formatted_address" : "14 Binswood Avenue, East York, ON M4C 3N3, Canada",
         "geometry" : {
            "bounds" : {
               "northeast" : {
                  "lat" : 43.690344,
                  "lng" : -79.3223928
               },
               "southwest" : {
                  "lat" : 43.69034,
                  "lng" : -79.3224104
               }
            },
            "location" : {
               "lat" : 43.69034,
               "lng" : -79.3224104
            },
            "location_type" : "RANGE_INTERPOLATED",
            "viewport" : {
               "northeast" : {
                  "lat" : 43.6916909802915,
                  "lng" : -79.32105261970848
               },
               "southwest" : {
                  "lat" : 43.6889930197085,
                  "lng" : -79.3237505802915
               }
            }
         },
         "types" : [ "street_address" ]
      }
   ],
   "status" : "OK"
}
