{
   "results" : [
      {
         "address_components" : [
            {
               "long_name" : "90",
               "short_name" : "90",
               "types" : [ "street_number" ]
            },
            {
               "long_name" : "Albertus Avenue",
               "short_name" : "Albertus Ave",
               "types" : [ "route" ]
            },
            {
               "long_name" : "Lytton Park",
               "short_name" : "Lytton Park",
               "types" : [ "neighborhood", "political" ]
            },
            {
               "long_name" : "Old Toronto",
               "short_name" : "Old Toronto",
               "types" : [ "sublocality", "political" ]
            },
            {
               "long_name" : "Toronto",
               "short_name" : "Toronto",
               "types" : [ "locality", "political" ]
            },
            {
               "long_name" : "Toronto Division",
               "short_name" : "Toronto Division",
               "types" : [ "administrative_area_level_2", "political" ]
            },
            {
               "long_name" : "Ontario",
               "short_name" : "ON",
               "types" : [ "administrative_area_level_1", "political" ]
            },
            {
               "long_name" : "Canada",
               "short_name" : "CA",
               "types" : [ "country", "political" ]
            },
            {
               "long_name" : "M4R 1J7",
               "short_name" : "M4R 1J7",
               "types" : [ "postal_code" ]
            }
         ],
         "formatted_address" : "90 Albertus Avenue, Toronto, ON M4R 1J7, Canada",
         "geometry" : {
            "bounds" : {
               "northeast" : {
                  "lat" : 43.7140206,
                  "lng" : -79.4026477
               },
               "southwest" : {
                  "lat" : 43.7140077,
                  "lng" : -79.4026528
               }
            },
            "location" : {
               "lat" : 43.7140206,
               "lng" : -79.4026528
            },
            "location_type" : "RANGE_INTERPOLATED",
            "viewport" : {
               "northeast" : {
                  "lat" : 43.71536313029149,
                  "lng" : -79.4013012697085
               },
               "southwest" : {
                  "lat" : 43.71266516970849,
                  "lng" : -79.4039992302915
               }
            }
         },
         "types" : [ "street_address" ]
      }
   ],
   "status" : "OK"
}
