{
   "results" : [
      {
         "address_components" : [
            {
               "long_name" : "89",
               "short_name" : "89",
               "types" : [ "street_number" ]
            },
            {
               "long_name" : "Belsize Drive",
               "short_name" : "Belsize Dr",
               "types" : [ "route" ]
            },
            {
               "long_name" : "Davisville",
               "short_name" : "Davisville",
               "types" : [ "neighborhood", "political" ]
            },
            {
               "long_name" : "Old Toronto",
               "short_name" : "Old Toronto",
               "types" : [ "sublocality", "political" ]
            },
            {
               "long_name" : "Toronto",
               "short_name" : "Toronto",
               "types" : [ "locality", "political" ]
            },
            {
               "long_name" : "Toronto Division",
               "short_name" : "Toronto Division",
               "types" : [ "administrative_area_level_2", "political" ]
            },
            {
               "long_name" : "Ontario",
               "short_name" : "ON",
               "types" : [ "administrative_area_level_1", "political" ]
            },
            {
               "long_name" : "Canada",
               "short_name" : "CA",
               "types" : [ "country", "political" ]
            },
            {
               "long_name" : "M4S 2H1",
               "short_name" : "M4S 2H1",
               "types" : [ "postal_code" ]
            }
         ],
         "formatted_address" : "89 Belsize Drive, Toronto, ON M4S 2H1, Canada",
         "geometry" : {
            "location" : {
               "lat" : 43.7010546,
               "lng" : -79.3926841
            },
            "location_type" : "ROOFTOP",
            "viewport" : {
               "northeast" : {
                  "lat" : 43.7024035802915,
                  "lng" : -79.39133511970849
               },
               "southwest" : {
                  "lat" : 43.6997056197085,
                  "lng" : -79.39403308029151
               }
            }
         },
         "types" : [ "street_address" ]
      }
   ],
   "status" : "OK"
}
