{
   "results" : [
      {
         "address_components" : [
            {
               "long_name" : "192",
               "short_name" : "192",
               "types" : [ "street_number" ]
            },
            {
               "long_name" : "Brookdale Avenue",
               "short_name" : "Brookdale Ave",
               "types" : [ "route" ]
            },
            {
               "long_name" : "Bedford Park",
               "short_name" : "Bedford Park",
               "types" : [ "neighborhood", "political" ]
            },
            {
               "long_name" : "Old Toronto",
               "short_name" : "Old Toronto",
               "types" : [ "sublocality", "political" ]
            },
            {
               "long_name" : "Toronto",
               "short_name" : "Toronto",
               "types" : [ "locality", "political" ]
            },
            {
               "long_name" : "Toronto Division",
               "short_name" : "Toronto Division",
               "types" : [ "administrative_area_level_2", "political" ]
            },
            {
               "long_name" : "Ontario",
               "short_name" : "ON",
               "types" : [ "administrative_area_level_1", "political" ]
            },
            {
               "long_name" : "Canada",
               "short_name" : "CA",
               "types" : [ "country", "political" ]
            },
            {
               "long_name" : "M5M 1P5",
               "short_name" : "M5M 1P5",
               "types" : [ "postal_code" ]
            }
         ],
         "formatted_address" : "192 Brookdale Avenue, Toronto, ON M5M 1P5, Canada",
         "geometry" : {
            "bounds" : {
               "northeast" : {
                  "lat" : 43.7286708,
                  "lng" : -79.4096297
               },
               "southwest" : {
                  "lat" : 43.728658,
                  "lng" : -79.40963479999999
               }
            },
            "location" : {
               "lat" : 43.7286708,
               "lng" : -79.40963479999999
            },
            "location_type" : "RANGE_INTERPOLATED",
            "viewport" : {
               "northeast" : {
                  "lat" : 43.7300133802915,
                  "lng" : -79.40828326970849
               },
               "southwest" : {
                  "lat" : 43.7273154197085,
                  "lng" : -79.41098123029151
               }
            }
         },
         "types" : [ "street_address" ]
      }
   ],
   "status" : "OK"
}
