{
   "results" : [
      {
         "address_components" : [
            {
               "long_name" : "282",
               "short_name" : "282",
               "types" : [ "street_number" ]
            },
            {
               "long_name" : "Bain Avenue",
               "short_name" : "Bain Ave",
               "types" : [ "route" ]
            },
            {
               "long_name" : "Riverdale",
               "short_name" : "Riverdale",
               "types" : [ "neighborhood", "political" ]
            },
            {
               "long_name" : "Old Toronto",
               "short_name" : "Old Toronto",
               "types" : [ "sublocality", "political" ]
            },
            {
               "long_name" : "Toronto",
               "short_name" : "Toronto",
               "types" : [ "locality", "political" ]
            },
            {
               "long_name" : "Toronto Division",
               "short_name" : "Toronto Division",
               "types" : [ "administrative_area_level_2", "political" ]
            },
            {
               "long_name" : "Ontario",
               "short_name" : "ON",
               "types" : [ "administrative_area_level_1", "political" ]
            },
            {
               "long_name" : "Canada",
               "short_name" : "CA",
               "types" : [ "country", "political" ]
            },
            {
               "long_name" : "M4J 1B9",
               "short_name" : "M4J 1B9",
               "types" : [ "postal_code" ]
            }
         ],
         "formatted_address" : "282 Bain Avenue, Toronto, ON M4J 1B9, Canada",
         "geometry" : {
            "location" : {
               "lat" : 43.6731929,
               "lng" : -79.34192039999999
            },
            "location_type" : "ROOFTOP",
            "viewport" : {
               "northeast" : {
                  "lat" : 43.67454188029151,
                  "lng" : -79.34057141970848
               },
               "southwest" : {
                  "lat" : 43.67184391970851,
                  "lng" : -79.34326938029149
               }
            }
         },
         "types" : [ "street_address" ]
      }
   ],
   "status" : "OK"
}
